pykamek/__init__.py
pykamek/__main__.py
pykamek/addressmapper.py
pykamek/elfenums.py
pykamek/exceptions.py
pykamek/ioreader.py
pykamek/kamek.py
pykamek/kmcommands.py
pykamek/kmhooks.py
pykamek/kmword.py
pykamek/linker.py
pykamek/readelf.py
pykamek/versionmap.py
pykamek-1.0.2.dist-info/LICENSE
pykamek-1.0.2.dist-info/METADATA
pykamek-1.0.2.dist-info/WHEEL
pykamek-1.0.2.dist-info/top_level.txt
pykamek-1.0.2.dist-info/RECORD
